date_simple/__init__.py
date_simple/date_simple.py
date_simple-0.1.dist-info/METADATA
date_simple-0.1.dist-info/WHEEL
date_simple-0.1.dist-info/top_level.txt
date_simple-0.1.dist-info/RECORD
